xia_gpt_prompts/__init__.py
xia_gpt_prompts/actor.cpython-311-darwin.so
xia_gpt_prompts/campaign.cpython-311-darwin.so
xia_gpt_prompts/dialog.cpython-311-darwin.so
xia_gpt_prompts/knowledge.cpython-311-darwin.so
xia_gpt_prompts/mission.cpython-311-darwin.so
xia_gpt_prompts/task.cpython-311-darwin.so
xia_gpt_prompts/templates/missions/architecture_design.json
xia_gpt_prompts/templates/missions/product_design.json
xia_gpt_prompts/templates/missions/project_management.json
xia_gpt_prompts/templates/missions/python_development.json
xia_gpt_prompts/templates/prompts/developer_python.prompt
xia_gpt_prompts/templates/prompts/generator.prompt
xia_gpt_prompts/templates/tasks/design/data_structures_and_interface_definitions.prompt
xia_gpt_prompts/templates/tasks/design/development_task_list.prompt
xia_gpt_prompts/templates/tasks/design/implement_approach.prompt
xia_gpt_prompts/templates/tasks/design/logic_analysis.prompt
xia_gpt_prompts/templates/tasks/design/program_call_flow.prompt
xia_gpt_prompts/templates/tasks/design/python_package_name.prompt
xia_gpt_prompts/templates/tasks/design/required_python_third_party_packages.prompt
xia_gpt_prompts/templates/tasks/design/shared_knowledge.prompt
xia_gpt_prompts/templates/tasks/design/source_code_file_list.prompt
xia_gpt_prompts/templates/tasks/develop/python_general.prompt
xia_gpt_prompts/templates/tasks/requirements/product_goals.prompt
xia_gpt_prompts/templates/tasks/requirements/requirement_analysis.prompt
xia_gpt_prompts/templates/tasks/requirements/user_stories.prompt
xia_gpt_prompts-0.0.12.dist-info/LICENSE.txt
xia_gpt_prompts-0.0.12.dist-info/METADATA
xia_gpt_prompts-0.0.12.dist-info/WHEEL
xia_gpt_prompts-0.0.12.dist-info/top_level.txt
xia_gpt_prompts-0.0.12.dist-info/RECORD
