Metadata-Version: 2.1
Name: xia-gpt-prompts
Version: 0.0.12
Summary: UNKNOWN
Home-page: https://develop.x-i-a.com/docs/xia-gpt-prompts/0.0.12/index.html
Author: X-I-A
Author-email: admin@x-i-a.com
License: UNKNOWN
Platform: UNKNOWN
Requires-Python: >=3.9
License-File: LICENSE.txt
Requires-Dist: xia-engine
Requires-Dist: xia-gpt
Requires-Dist: xia-gpt-openai
